pyqtgraph_ext-2025.4.9.dist-info/METADATA
pyqtgraph_ext-2025.4.9.dist-info/WHEEL
pyqtgraph_ext-2025.4.9.dist-info/entry_points.txt
pyqtgraph_ext-2025.4.9.dist-info/licenses/LICENSE
pyqtgraph_ext/AxisRegion.py
pyqtgraph_ext/AxisRegionTreeItem.py
pyqtgraph_ext/AxisRegionTreeModel.py
pyqtgraph_ext/AxisRegionTreeView.py
pyqtgraph_ext/CurveFit.py
pyqtgraph_ext/Figure.py
pyqtgraph_ext/Graph.py
pyqtgraph_ext/GraphStyle.py
pyqtgraph_ext/Plot.py
pyqtgraph_ext/PlotGrid.py
pyqtgraph_ext/View.py
pyqtgraph_ext/__init__.py
pyqtgraph_ext-2025.4.9.dist-info/RECORD
