Metadata-Version: 2.1
Name: pyqtgraph-ext
Version: 2025.4.9
Summary: Collection of PyQtGraph widgets/tools.
Keywords: pyqtgraph,pyqt,pyside,widget,plot,graph,chart
Author-Email: Marcel Goldschen-Ohm <goldschen-ohm@utexas.edu>
Classifier: Development Status :: 4 - Beta
Classifier: Intended Audience :: Developers
Classifier: License :: OSI Approved :: MIT License
Classifier: Programming Language :: Python :: 3 :: Only
Project-URL: homepage, https://github.com/marcel-goldschen-ohm/pyqtgraph-ext
Project-URL: repository, https://github.com/marcel-goldschen-ohm/pyqtgraph-ext
Project-URL: issues, https://github.com/marcel-goldschen-ohm/pyqtgraph-ext/issues
Requires-Python: >=3.10
Requires-Dist: numpy>=1.26.2
Requires-Dist: scipy>=1.11.4
Requires-Dist: lmfit>=1.2.2
Requires-Dist: qtpy>=2.4.1
Requires-Dist: qtawesome>=1.4.0
Requires-Dist: pyqtgraph>=0.13.3
Requires-Dist: pyqt-ext>=2025.4.9.2
